megfile/__init__.py
megfile/cli.py
megfile/config.py
megfile/errors.py
megfile/fs_path.py
megfile/hdfs_path.py
megfile/http_path.py
megfile/interfaces.py
megfile/pathlike.py
megfile/s3_path.py
megfile/sftp2_path.py
megfile/sftp_path.py
megfile/smart.py
megfile/smart_path.py
megfile/stdio_path.py
megfile/version.py
megfile/webdav_path.py
megfile/lib/__init__.py
megfile/lib/base_memory_handler.py
megfile/lib/base_prefetch_reader.py
megfile/lib/combine_reader.py
megfile/lib/compare.py
megfile/lib/compat.py
megfile/lib/fnmatch.py
megfile/lib/glob.py
megfile/lib/hdfs_prefetch_reader.py
megfile/lib/hdfs_tools.py
megfile/lib/http_prefetch_reader.py
megfile/lib/joinpath.py
megfile/lib/lazy_handler.py
megfile/lib/s3_buffered_writer.py
megfile/lib/s3_cached_handler.py
megfile/lib/s3_limited_seekable_writer.py
megfile/lib/s3_memory_handler.py
megfile/lib/s3_pipe_handler.py
megfile/lib/s3_prefetch_reader.py
megfile/lib/s3_share_cache_reader.py
megfile/lib/shadow_handler.py
megfile/lib/stdio_handler.py
megfile/lib/url.py
megfile/lib/webdav_memory_handler.py
megfile/lib/webdav_prefetch_reader.py
megfile/utils/__init__.py
megfile/utils/atomic.py
megfile/utils/mutex.py
megfile-5.0.6.dist-info/licenses/LICENSE
megfile-5.0.6.dist-info/licenses/LICENSE.pyre
megfile-5.0.6.dist-info/METADATA
megfile-5.0.6.dist-info/WHEEL
megfile-5.0.6.dist-info/entry_points.txt
megfile-5.0.6.dist-info/top_level.txt
megfile-5.0.6.dist-info/RECORD
