Metadata-Version: 2.4
Name: megfile
Version: 5.0.6
Summary: Megvii file operation library
Author-email: megvii-reng <megvii-reng@googlegroups.com>
Project-URL: Homepage, https://github.com/megvii-research/megfile
Classifier: Development Status :: 5 - Production/Stable
Classifier: Environment :: Console
Classifier: Intended Audience :: Developers
Classifier: License :: OSI Approved :: Apache Software License
Classifier: Operating System :: POSIX :: Linux
Classifier: Programming Language :: Python
Classifier: Programming Language :: Python :: 3
Classifier: Programming Language :: Python :: 3 :: Only
Classifier: Programming Language :: Python :: 3.10
Classifier: Programming Language :: Python :: 3.11
Classifier: Programming Language :: Python :: 3.12
Classifier: Programming Language :: Python :: 3.13
Classifier: Programming Language :: Python :: 3.14
Requires-Python: >=3.10
License-File: LICENSE
License-File: LICENSE.pyre
Requires-Dist: boto3
Requires-Dist: botocore>=1.13.0
Requires-Dist: requests
Requires-Dist: paramiko<4.0.0
Requires-Dist: tqdm
Requires-Dist: pyyaml
Provides-Extra: hdfs
Requires-Dist: hdfs; extra == "hdfs"
Provides-Extra: sftp2
Requires-Dist: ssh2-python>=1.0.0; extra == "sftp2"
Provides-Extra: webdav
Requires-Dist: webdavclient3>=3.0.0; extra == "webdav"
Requires-Dist: python-dateutil; extra == "webdav"
Provides-Extra: cli
Requires-Dist: click; extra == "cli"
Dynamic: license-file
